dxc_ai_test/ai.py
dxc_ai_test-1.0.0.dist-info/LICENSE
dxc_ai_test-1.0.0.dist-info/METADATA
dxc_ai_test-1.0.0.dist-info/WHEEL
dxc_ai_test-1.0.0.dist-info/entry_points.txt
dxc_ai_test-1.0.0.dist-info/top_level.txt
dxc_ai_test-1.0.0.dist-info/RECORD
